<?xml version="1.0" encoding="utf-8"?>
<cms.webpageurlpath>
  <WebPageUrlPath>Main</WebPageUrlPath>
  <WebPageUrlPathContentLanguageID>
    <CodeName>en</CodeName>
    <GUID>1dbc0a03-c8cc-4eaa-87a1-c3289331f638</GUID>
    <ObjectType>cms.contentlanguage</ObjectType>
  </WebPageUrlPathContentLanguageID>
  <WebPageUrlPathGUID>95d1a5e9-2d1d-483b-ab4d-b046b6409510</WebPageUrlPathGUID>
  <WebPageUrlPathHash>
    <![CDATA[9EF231001E50043A7358C0E0CE5CF1B6B0168A95C933D0FE7CB9F3ED307BE651]]>
  </WebPageUrlPathHash>
  <WebPageUrlPathIsCanonical>True</WebPageUrlPathIsCanonical>
  <WebPageUrlPathIsDraft>False</WebPageUrlPathIsDraft>
  <WebPageUrlPathIsLatest>True</WebPageUrlPathIsLatest>
  <WebPageUrlPathType>0</WebPageUrlPathType>
  <WebPageUrlPathWebPageItemID>
    <CodeName>Main-ziqg88yf</CodeName>
    <GUID>9494e33c-6d14-4c2b-958a-bd5eeb225f11</GUID>
    <ObjectType>cms.webpageitem</ObjectType>
  </WebPageUrlPathWebPageItemID>
  <WebPageUrlPathWebsiteChannelID>
    <GUID>ce54dd23-44b3-44b8-acc4-d9713953a7fc</GUID>
    <ObjectType>cms.websitechannel</ObjectType>
    <Parent>
      <CodeName>NovusOnePages</CodeName>
      <GUID>165e7dc9-83bb-429a-b3a8-b55b46bd3e10</GUID>
      <ObjectType>cms.channel</ObjectType>
    </Parent>
  </WebPageUrlPathWebsiteChannelID>
</cms.webpageurlpath>